drawtf.py
app/__init__.py
app/__main__.py
app/azure/__init__.py
app/azure/azure.py
app/azure/azure_resource_factory.py
app/azure/resources/__init__.py
app/azure/resources/azurerm_api_management.py
app/azure/resources/azurerm_api_management_api.py
app/azure/resources/azurerm_api_management_certificate.py
app/azure/resources/azurerm_api_management_custom_domain.py
app/azure/resources/azurerm_api_management_diagnostic.py
app/azure/resources/azurerm_api_management_logger.py
app/azure/resources/azurerm_app_configuration.py
app/azure/resources/azurerm_app_service.py
app/azure/resources/azurerm_app_service_plan.py
app/azure/resources/azurerm_app_service_slot.py
app/azure/resources/azurerm_application_insights.py
app/azure/resources/azurerm_container_app.py
app/azure/resources/azurerm_container_app_environment.py
app/azure/resources/azurerm_container_group.py
app/azure/resources/azurerm_container_registry.py
app/azure/resources/azurerm_cosmosdb_account.py
app/azure/resources/azurerm_cosmosdb_sql_container.py
app/azure/resources/azurerm_cosmosdb_sql_database.py
app/azure/resources/azurerm_databricks_workspace.py
app/azure/resources/azurerm_function_app.py
app/azure/resources/azurerm_function_app_slot.py
app/azure/resources/azurerm_key_vault.py
app/azure/resources/azurerm_kubernetes_cluster.py
app/azure/resources/azurerm_linux_function_app.py
app/azure/resources/azurerm_log_analytics_workspace.py
app/azure/resources/azurerm_logic_app_workflow.py
app/azure/resources/azurerm_mssql_database.py
app/azure/resources/azurerm_mssql_server.py
app/azure/resources/azurerm_network_security_group.py
app/azure/resources/azurerm_resource_group.py
app/azure/resources/azurerm_service_plan.py
app/azure/resources/azurerm_servicebus_namespace.py
app/azure/resources/azurerm_servicebus_queue.py
app/azure/resources/azurerm_servicebus_subscription.py
app/azure/resources/azurerm_servicebus_topic.py
app/azure/resources/azurerm_signalr_service.py
app/azure/resources/azurerm_static_site.py
drawtf-0.12.0.dist-info/LICENSE
drawtf-0.12.0.dist-info/METADATA
drawtf-0.12.0.dist-info/WHEEL
drawtf-0.12.0.dist-info/entry_points.txt
drawtf-0.12.0.dist-info/top_level.txt
drawtf-0.12.0.dist-info/RECORD
